pyDictH5/__init__.py
pyDictH5/_version.py
pyDictH5/base.py
pyDictH5/dep.py
pyDictH5/io.py
pyDictH5/pkl.py
pyDictH5/tabular.py
pyDictH5-0.2.3.dist-info/LICENSE.txt
pyDictH5-0.2.3.dist-info/METADATA
pyDictH5-0.2.3.dist-info/WHEEL
pyDictH5-0.2.3.dist-info/top_level.txt
pyDictH5-0.2.3.dist-info/RECORD
