Metadata-Version: 2.1
Name: pyDictH5
Version: 0.2.3
Summary: UNKNOWN
Home-page: http://github.com/lkilcher/pyDictH5
Author: Levi Kilcher
Author-email: levi.kilcher@nrel.gov
License: UNKNOWN
Platform: UNKNOWN
Classifier: Development Status :: 3 - Alpha
Classifier: Intended Audience :: Science/Research
Classifier: License :: OSI Approved :: Apache Software License
Classifier: Natural Language :: English
License-File: LICENSE.txt
Requires-Dist: h5py
Requires-Dist: numpy
